CHANGELOG.rst
README.rst
quiz/__init__.py
quiz/build.py
quiz/execution.py
quiz/schema.py
quiz/types.py
quiz/utils.py
quiz-0.3.2.dist-info/LICENSE
quiz-0.3.2.dist-info/METADATA
quiz-0.3.2.dist-info/WHEEL
quiz-0.3.2.dist-info/RECORD
