Metadata-Version: 2.1
Name: quiz
Version: 0.3.2
Summary: Capable GraphQL client
Home-page: https://github.com/ariebovenberg/quiz
License: MIT
Keywords: http,async,graphql
Author: Arie Bovenberg
Author-email: a.c.bovenberg@gmail.com
Requires-Python: >=3.7,<4.0
Classifier: Development Status :: 3 - Alpha
Classifier: Intended Audience :: Developers
Classifier: License :: OSI Approved :: Apache Software License
Classifier: License :: OSI Approved :: MIT License
Classifier: Programming Language :: Python :: 3
Classifier: Programming Language :: Python :: 3.7
Classifier: Programming Language :: Python :: 3.8
Classifier: Programming Language :: Python :: 3.9
Classifier: Programming Language :: Python :: 3.10
Classifier: Programming Language :: Python :: 3.11
Classifier: Programming Language :: Python :: 3.10
Classifier: Programming Language :: Python :: 3.11
Classifier: Programming Language :: Python :: 3.7
Classifier: Programming Language :: Python :: 3.8
Classifier: Programming Language :: Python :: 3.9
Requires-Dist: gentools (>=1.2.0,<2.0.0)
Requires-Dist: importlib-metadata ; python_version < "3.8"
Requires-Dist: snug (>=2.2.0,<3.0.0)
Project-URL: Repository, https://github.com/ariebovenberg/quiz
